README.md
setup.cfg
setup.py
simple_tensor/__init__.py
simple_tensor/tensor_losses.py
simple_tensor/tensor_metrics.py
simple_tensor/tensor_operations.py
simple_tensor.egg-info/PKG-INFO
simple_tensor.egg-info/SOURCES.txt
simple_tensor.egg-info/dependency_links.txt
simple_tensor.egg-info/top_level.txt
simple_tensor/face_recog/__init__.py
simple_tensor/face_recog/insight_face.py
simple_tensor/networks/__init__.py
simple_tensor/networks/densenet.py
simple_tensor/networks/inception_utils.py
simple_tensor/networks/inception_v4.py
simple_tensor/networks/modified_resnet_v2.py
simple_tensor/networks/resnet_utils.py
simple_tensor/networks/resnet_v1.py
simple_tensor/networks/resnet_v2.py
simple_tensor/object_detector/__init__.py
simple_tensor/object_detector/detector_utils.py
simple_tensor/object_detector/yolo.py
simple_tensor/object_detector/yolo2voc.py
simple_tensor/rnn_packs/__init__.py
simple_tensor/rnn_packs/lstm.py
simple_tensor/segmentation/__init__.py
simple_tensor/segmentation/deeplab.py
simple_tensor/segmentation/unet.py
simple_tensor/transfer_learning/__init__.py
simple_tensor/transfer_learning/image_recognition.py