Metadata-Version: 2.1
Name: simple_tensor
Version: 0.7.14
Summary: a simple package for handling tensorflow tensor
Home-page: UNKNOWN
Author: fatchur_rahman
Author-email: fatchur.rahman1@gmail.com
License: UNKNOWN
Platform: UNKNOWN
